rbx/__init__.py
rbx/__version__.py
rbx/annotations.py
rbx/autoenum.py
rbx/box/__init__.py
rbx/box/builder.py
rbx/box/cd.py
rbx/box/checkers.py
rbx/box/cli.py
rbx/box/code.py
rbx/box/compile.py
rbx/box/contest/__init__.py
rbx/box/contest/build_contest_statements.py
rbx/box/contest/contest_package.py
rbx/box/contest/contest_utils.py
rbx/box/contest/main.py
rbx/box/contest/schema.py
rbx/box/contest/statement_overriding.py
rbx/box/contest/statements.py
rbx/box/creation.py
rbx/box/deferred.py
rbx/box/download.py
rbx/box/dump_cli_docs.py
rbx/box/dump_schemas.py
rbx/box/environment.py
rbx/box/exception.py
rbx/box/extensions.py
rbx/box/fields.py
rbx/box/formatting.py
rbx/box/generation_schema.py
rbx/box/generator_script_handlers.py
rbx/box/generators.py
rbx/box/git_utils.py
rbx/box/global_package.py
rbx/box/header.py
rbx/box/lang.py
rbx/box/lazy_importing_main.py
rbx/box/limits_info.py
rbx/box/linting.py
rbx/box/main.py
rbx/box/naming.py
rbx/box/package.py
rbx/box/packaging/__init__.py
rbx/box/packaging/boca/__init__.py
rbx/box/packaging/boca/boca_language_utils.py
rbx/box/packaging/boca/boca_outcome_utils.py
rbx/box/packaging/boca/extension.py
rbx/box/packaging/boca/packager.py
rbx/box/packaging/contest_main.py
rbx/box/packaging/importer.py
rbx/box/packaging/main.py
rbx/box/packaging/moj/packager.py
rbx/box/packaging/packager.py
rbx/box/packaging/pkg/packager.py
rbx/box/packaging/polygon/extension.py
rbx/box/packaging/polygon/importer.py
rbx/box/packaging/polygon/packager.py
rbx/box/packaging/polygon/polygon_api.py
rbx/box/packaging/polygon/test.py
rbx/box/packaging/polygon/upload.py
rbx/box/packaging/polygon/utils.py
rbx/box/packaging/polygon/xml_schema.py
rbx/box/presets/__init__.py
rbx/box/presets/fetch.py
rbx/box/presets/lock_schema.py
rbx/box/presets/schema.py
rbx/box/remote.py
rbx/box/rendering.py
rbx/box/retries.py
rbx/box/safeeval.py
rbx/box/sanitizers/issue_stack.py
rbx/box/sanitizers/warning_stack.py
rbx/box/schema.py
rbx/box/setter_config.py
rbx_cp-0.23.0.dist-info/LICENSE
rbx_cp-0.23.0.dist-info/METADATA
rbx_cp-0.23.0.dist-info/WHEEL
rbx_cp-0.23.0.dist-info/entry_points.txt
rbx_cp-0.23.0.dist-info/RECORD
