Metadata-Version: 2.3
Name: rbx.cp
Version: 0.23.0
Summary: 
Author: Roberto Sales
Requires-Python: >=3.9.1,<4.0.0
Classifier: Programming Language :: Python :: 3
Classifier: Programming Language :: Python :: 3.10
Classifier: Programming Language :: Python :: 3.11
Classifier: Programming Language :: Python :: 3.12
Classifier: Programming Language :: Python :: 3.13
Requires-Dist: aiofiles (>=24.1.0,<25.0.0)
Requires-Dist: async-lru (>=2.0.5,<3.0.0)
Requires-Dist: beautifulsoup4 (>=4.13.4,<5.0.0)
Requires-Dist: chardet (>=5.2.0,<6.0.0)
Requires-Dist: colour (>=0.1.5,<0.2.0)
Requires-Dist: dateparser (>=1.2.1,<2.0.0)
Requires-Dist: deepmerge (>=2.0,<3.0)
Requires-Dist: fastapi (>=0.115.8,<0.116.0)
Requires-Dist: filelock (>=3.14.0,<4.0.0)
Requires-Dist: gitignore-parser (>=0.1.12,<0.2.0)
Requires-Dist: gitpython (>=3.1.43,<4.0.0)
Requires-Dist: iso639-lang (>=2.6.1,<3.0.0)
Requires-Dist: jinja2 (>=3.1.4,<4.0.0)
Requires-Dist: lark (>=1.2.2,<2.0.0)
Requires-Dist: latexbuild (>=0.2.2,<0.3.0)
Requires-Dist: lz4 (>=4.4.4,<5.0.0)
Requires-Dist: mechanize (>=0.4.10,<0.5.0)
Requires-Dist: more-itertools (>=10.5.0,<11.0.0)
Requires-Dist: nest-asyncio (>=1.6.0,<2.0.0)
Requires-Dist: openai-agents (>=0.3.0,<0.4.0)
Requires-Dist: ordered-set (>=4.1.0,<5.0.0)
Requires-Dist: packaging (>=25.0,<26.0)
Requires-Dist: psutil (>=7.0.0,<8.0.0)
Requires-Dist: pydantic (>=2.11.7,<3.0.0)
Requires-Dist: pydantic-xml[lxml] (>=2.11.0,<3.0.0)
Requires-Dist: pypandoc (>=1.15,<2.0)
Requires-Dist: pyte (>=0.8.2,<0.9.0)
Requires-Dist: python-dotenv (>=1.1.1,<2.0.0)
Requires-Dist: pyyaml (>=6.0.1,<7.0.0)
Requires-Dist: questionary (>=2.1.0,<3.0.0)
Requires-Dist: requests (>=2.32.3,<3.0.0)
Requires-Dist: rich (>=13.9.4,<14.0.0)
Requires-Dist: ruamel-yaml (>=0.18.14,<0.19.0)
Requires-Dist: ruyaml (>=0.91.0,<0.92.0)
Requires-Dist: semver (>=3.0.4,<4.0.0)
Requires-Dist: simpleeval (>=1.0.3,<2.0.0)
Requires-Dist: sqlitedict (>=2.1.0,<3.0.0)
Requires-Dist: syncer (>=2.0.3,<3.0.0)
Requires-Dist: texsoup (>=0.3.1,<0.4.0)
Requires-Dist: textual (>=3.1.1,<4.0.0)
Requires-Dist: textual-serve (>=1.1.2,<2.0.0)
Requires-Dist: throttlex (>=1.0.0,<2.0.0)
Requires-Dist: typer (>=0.15.1,<0.16.0)
Requires-Dist: typing-extensions (>=4.14.1,<5.0.0)
Requires-Dist: uvicorn (>=0.35.0,<0.36.0)
Requires-Dist: yamlfix (>=1.17.0,<2.0.0)
